bust/__init__.py
bust/__main__.py
bust/_version.py
bust/bus.py
bust/bus_vhdl_gen.py
bust/documentation.py
bust/editor.py
bust/exceptions.py
bust/field.py
bust/generation.py
bust/header.py
bust/module.py
bust/module_vhdl_gen.py
bust/register.py
bust/settings.py
bust/testbench.py
bust/utils.py
bust/vhdl.py
tests/__init__.py
tests/test_suite.py
bust-0.9.4.dist-info/LICENSE
bust-0.9.4.dist-info/METADATA
bust-0.9.4.dist-info/WHEEL
bust-0.9.4.dist-info/entry_points.txt
bust-0.9.4.dist-info/top_level.txt
bust-0.9.4.dist-info/RECORD
