Metadata-Version: 2.1
Name: bust
Version: 0.9.4
Summary: Utility for simply creating and modifying VHDL bus slave modules
Home-page: http://github.com/olagrottvik/bust
Author: Ola Groettvik
Author-email: olagrottvik@gmail.com
License: MIT
Keywords: vhdl,bus,axi
Platform: UNKNOWN
Requires-Python: ~=3.4
Requires-Dist: docopt (>=0.6.2)
Requires-Dist: pylatexenc (>=1.2)
Requires-Dist: curses-menu
Requires-Dist: PrettyTable
Provides-Extra: dev
Requires-Dist: pytest ; extra == 'dev'
Requires-Dist: pylint ; extra == 'dev'
